aur_git.py
aur_git-0.0.2.dist-info/LICENSE
aur_git-0.0.2.dist-info/METADATA
aur_git-0.0.2.dist-info/WHEEL
aur_git-0.0.2.dist-info/top_level.txt
aur_git-0.0.2.dist-info/RECORD
