Metadata-Version: 2.1
Name: aur-git
Version: 0.0.2
Summary: Retrieve and install an AUR package from Arch User Repository (AUR).
Home-page: https://www.techtum.dev
Author: siphr
Author-email: pypi@techtum.dev
License: UNKNOWN
Project-URL: Bug Tracker, https://github.com/siphr/aur-git
Platform: UNKNOWN
Classifier: Programming Language :: Python :: 3
Classifier: License :: OSI Approved :: MIT License
Classifier: Operating System :: OS Independent
Requires-Python: >=3.6
License-File: LICENSE
